{
  "product": [
    {
      "title": "Mảng cầu đá xoay",
      "image": "https://phuclong.com.vn/uploads/dish/6a3bbf6dac792d-mangcaudaxay.png",
      "id": "1",
      "price": 50
    },
    {
      "title": "Trà sửa mảng cầu",
      "image": "https://phuclong.com.vn/uploads/dish/4ce1825cbd1978-trasuamc.png",
      "id": "2",
      "price": 40
    },
    {
      "title": "Trà Lucky",
      "image": "https://phuclong.com.vn/uploads/dish/f48194a2a92877-luckytea.png",
      "id": "3",
      "price": 30
    },
    {
      "title": "Cafe đen",
      "image": "https://phuclong.com.vn/uploads/dish/4521f4c77fc38a-cf67efb06d5aa504fc4b.png",
      "id": "4",
      "price": 35
    },
    {
      "title": "Cafe sửa",
      "image": "https://phuclong.com.vn/uploads/dish/8ebb07f0eeccc1-resize_damdadunggu07.png",
      "id": "5",
      "price": 45
    },
    {
      "title": "Hồng trà đào",
      "image": "https://phuclong.com.vn/uploads/dish/3937476a64a213-trophclong.png",
      "id": "6",
      "price": 25
    },
    {
      "title": "Bạc xỉu",
      "image": "https://phuclong.com.vn/uploads/dish/24d0961b7dba35-chocolatephclong.png",
      "id": "7",
      "price": 55
    },
    {
      "title": "Sữa chua phúc bồn   ",
      "image": "https://phuclong.com.vn/uploads/dish/4136b3715bff3e-sachuaphcbntccamphclong.png",
      "id": "8",
      "price": 60
    },
    {
      "title": "Cappuccino",
      "image": "https://phuclong.com.vn/uploads/dish/90405a9f256f11-cafe5mon04.png",
      "id": "9",
      "price": 70
    },
    {
      "title": "Latte",
      "image": "https://phuclong.com.vn/uploads/dish/8a92bb4b37c012-cafe5mon01.png",
      "id": "10",
      "price": 65
    },
    {
      "title": "Trà Vải Lài",
      "image": "https://phuclong.com.vn/uploads/dish/063555c21c4206-trviliphclong.png",
      "id": "11",
      "price": 50
    },
    {
      "title": "Trà Sữa Nhãn Sen",
      "image": "https://phuclong.com.vn/uploads/dish/e3a453a57402ee-65000307trsanhnsen.png",
      "id": "12",
      "price": 55
    }
  ]
}
